{
    "min_scaled_matching_probability": 0.15930000000000002,
    "scaled_matching_probabilities": {
        "(0, 1)": 0.8433,
        "(0, 2)": 0.7605000000000001,
        "(0, 3)": 0.8397,
        "(0, 4)": 0.8451000000000001,
        "(0, 5)": 1.7118000000000002,
        "(0, 6)": 0.46440000000000003,
        "(0, 7)": 0.8145,
        "(0, 8)": 1.0629,
        "(0, 9)": 0.4302,
        "(1, 2)": 0.7236,
        "(1, 3)": 0.7911000000000001,
        "(1, 4)": 1.0602,
        "(1, 5)": 0.657,
        "(1, 6)": 0.7029000000000001,
        "(1, 7)": 0.6911999999999999,
        "(1, 8)": 1.0665,
        "(1, 9)": 0.8541000000000001,
        "(2, 3)": 1.0116,
        "(2, 4)": 0.7281000000000001,
        "(2, 5)": 0.15930000000000002,
        "(2, 6)": 0.9297000000000001,
        "(2, 7)": 0.43650000000000005,
        "(2, 8)": 0.8109000000000001,
        "(2, 9)": 2.1285,
        "(3, 4)": 0.7776000000000001,
        "(3, 5)": 1.1835000000000002,
        "(3, 6)": 1.4661,
        "(3, 7)": 0.7776000000000001,
        "(3, 8)": 0.7794,
        "(3, 9)": 0.7398,
        "(4, 5)": 0.7587,
        "(4, 6)": 0.7614000000000001,
        "(4, 7)": 1.5633000000000001,
        "(4, 8)": 0.6246,
        "(4, 9)": 1.0926,
        "(5, 6)": 0.7542000000000001,
        "(5, 7)": 1.2726,
        "(5, 8)": 0.7803,
        "(5, 9)": 0.7974,
        "(6, 7)": 0.8109000000000001,
        "(6, 8)": 1.6227,
        "(6, 9)": 0.3807,
        "(7, 8)": 0.7623000000000002,
        "(7, 9)": 0.7956000000000001,
        "(8, 9)": 0.7551000000000001
    },
    "matching_probabilities": {
        "(0, 1)": 0.0937,
        "(0, 2)": 0.0845,
        "(0, 3)": 0.0933,
        "(0, 4)": 0.0939,
        "(0, 5)": 0.1902,
        "(0, 6)": 0.0516,
        "(0, 7)": 0.0905,
        "(0, 8)": 0.1181,
        "(0, 9)": 0.0478,
        "(1, 2)": 0.0804,
        "(1, 3)": 0.0879,
        "(1, 4)": 0.1178,
        "(1, 5)": 0.073,
        "(1, 6)": 0.0781,
        "(1, 7)": 0.0768,
        "(1, 8)": 0.1185,
        "(1, 9)": 0.0949,
        "(2, 3)": 0.1124,
        "(2, 4)": 0.0809,
        "(2, 5)": 0.0177,
        "(2, 6)": 0.1033,
        "(2, 7)": 0.0485,
        "(2, 8)": 0.0901,
        "(2, 9)": 0.2365,
        "(3, 4)": 0.0864,
        "(3, 5)": 0.1315,
        "(3, 6)": 0.1629,
        "(3, 7)": 0.0864,
        "(3, 8)": 0.0866,
        "(3, 9)": 0.0822,
        "(4, 5)": 0.0843,
        "(4, 6)": 0.08460000000000001,
        "(4, 7)": 0.1737,
        "(4, 8)": 0.0694,
        "(4, 9)": 0.1214,
        "(5, 6)": 0.0838,
        "(5, 7)": 0.1414,
        "(5, 8)": 0.0867,
        "(5, 9)": 0.0886,
        "(6, 7)": 0.0901,
        "(6, 8)": 0.1803,
        "(6, 9)": 0.0423,
        "(7, 8)": 0.08470000000000001,
        "(7, 9)": 0.0884,
        "(8, 9)": 0.0839
    },
    "matching_counts": {
        "(0, 1)": 937.0,
        "(0, 2)": 845.0,
        "(0, 3)": 933.0,
        "(0, 4)": 939.0,
        "(0, 5)": 1902.0,
        "(0, 6)": 516.0,
        "(0, 7)": 905.0,
        "(0, 8)": 1181.0,
        "(0, 9)": 478.0,
        "(1, 2)": 804.0,
        "(1, 3)": 879.0000000000001,
        "(1, 4)": 1178.0,
        "(1, 5)": 730.0,
        "(1, 6)": 781.0,
        "(1, 7)": 768.0,
        "(1, 8)": 1185.0,
        "(1, 9)": 949.0,
        "(2, 3)": 1124.0,
        "(2, 4)": 809.0,
        "(2, 5)": 177.0,
        "(2, 6)": 1033.0,
        "(2, 7)": 485.0,
        "(2, 8)": 901.0,
        "(2, 9)": 2365.0,
        "(3, 4)": 864.0,
        "(3, 5)": 1315.0,
        "(3, 6)": 1629.0,
        "(3, 7)": 864.0000000000001,
        "(3, 8)": 866.0,
        "(3, 9)": 822.0,
        "(4, 5)": 843.0,
        "(4, 6)": 846.0000000000001,
        "(4, 7)": 1737.0,
        "(4, 8)": 694.0,
        "(4, 9)": 1214.0,
        "(5, 6)": 838.0,
        "(5, 7)": 1414.0,
        "(5, 8)": 867.0,
        "(5, 9)": 886.0,
        "(6, 7)": 901.0,
        "(6, 8)": 1803.0,
        "(6, 9)": 423.0,
        "(7, 8)": 847.0000000000001,
        "(7, 9)": 884.0,
        "(8, 9)": 839.0
    },
    "simulation_parameters": {
        "graph_file": "uniform_complete_10_order_0.json",
        "c_guarantee": 0.75,
        "experiment_name": "uniform_complete_10_order_0_si_c75_r70_sim10000",
        "average_edge_weight": 0.1111111111111111,
        "r": 0.7,
        "num_sim_instances": 10000,
        "rounding_scheme_class": "SimpleRecursiveRoundingScheme",
        "parallel": true
    }
}